{
  "authors":2,
  "changes":[
    0,
    0,
    0,
    0,
    0,
    0,
    0,
    0,
    1,
    0,
    0,
    0,
    0,
    0,
    0,
    0,
    0
  ],
  "era_topic":[
    "Abbasid",
    "Abbasid",
    "Abbasid",
    "Abbasid",
    "Abbasid",
    "Abbasid",
    "Abbasid",
    "Abbasid",
    "Abbasid",
    "Abbasid",
    "Abbasid",
    "Abbasid",
    "Abbasid",
    "Abbasid",
    "Abbasid",
    "Abbasid",
    "Abbasid",
    "Abbasid"
  ],
  "id":[
    "2_37",
    "2_1231",
    "2_1466",
    "2_464",
    "2_1098",
    "2_100",
    "2_391",
    "2_1133",
    "2_826",
    "1_43",
    "1_1707",
    "1_1295",
    "1_1729",
    "1_75",
    "1_793",
    "1_1435",
    "1_243",
    "1_83"
  ],
  "level":"hard",
  "linguistic_resource":[
    "Arabic Poetry Dataset",
    "Arabic Poetry Dataset",
    "Arabic Poetry Dataset",
    "Arabic Poetry Dataset",
    "Arabic Poetry Dataset",
    "Arabic Poetry Dataset",
    "Arabic Poetry Dataset",
    "Arabic Poetry Dataset",
    "Arabic Poetry Dataset",
    "Arabic Poetry Dataset",
    "Arabic Poetry Dataset",
    "Arabic Poetry Dataset",
    "Arabic Poetry Dataset",
    "Arabic Poetry Dataset",
    "Arabic Poetry Dataset",
    "Arabic Poetry Dataset",
    "Arabic Poetry Dataset",
    "Arabic Poetry Dataset"
  ],
  "multi-author":1,
  "paragraph-author-names":[
    "أبوالعلاء المعري",
    "أبوالعلاء المعري",
    "أبوالعلاء المعري",
    "أبوالعلاء المعري",
    "أبوالعلاء المعري",
    "أبوالعلاء المعري",
    "أبوالعلاء المعري",
    "أبوالعلاء المعري",
    "أبوالعلاء المعري",
    "ابن الرومي",
    "ابن الرومي",
    "ابن الرومي",
    "ابن الرومي",
    "ابن الرومي",
    "ابن الرومي",
    "ابن الرومي",
    "ابن الرومي",
    "ابن الرومي"
  ],
  "paragraph-author-numbers":[
    2,
    2,
    2,
    2,
    2,
    2,
    2,
    2,
    2,
    1,
    1,
    1,
    1,
    1,
    1,
    1,
    1,
    1
  ],
  "paragraph-author-numbers-transliteration":[
    ">bw AlElA’ AlmEry",
    ">bw AlElA’ AlmEry",
    ">bw AlElA’ AlmEry",
    ">bw AlElA’ AlmEry",
    ">bw AlElA’ AlmEry",
    ">bw AlElA’ AlmEry",
    ">bw AlElA’ AlmEry",
    ">bw AlElA’ AlmEry",
    ">bw AlElA’ AlmEry",
    "Abn Alrwmy",
    "Abn Alrwmy",
    "Abn Alrwmy",
    "Abn Alrwmy",
    "Abn Alrwmy",
    "Abn Alrwmy",
    "Abn Alrwmy",
    "Abn Alrwmy",
    "Abn Alrwmy"
  ],
  "url":[
    "https://github.com/inparallel/SaudiNewsNet",
    "https://github.com/inparallel/SaudiNewsNet",
    "https://github.com/inparallel/SaudiNewsNet",
    "https://github.com/inparallel/SaudiNewsNet",
    "https://github.com/inparallel/SaudiNewsNet",
    "https://github.com/inparallel/SaudiNewsNet",
    "https://github.com/inparallel/SaudiNewsNet",
    "https://github.com/inparallel/SaudiNewsNet",
    "https://github.com/inparallel/SaudiNewsNet",
    "https://github.com/inparallel/SaudiNewsNet",
    "https://github.com/inparallel/SaudiNewsNet",
    "https://github.com/inparallel/SaudiNewsNet",
    "https://github.com/inparallel/SaudiNewsNet",
    "https://github.com/inparallel/SaudiNewsNet",
    "https://github.com/inparallel/SaudiNewsNet",
    "https://github.com/inparallel/SaudiNewsNet",
    "https://github.com/inparallel/SaudiNewsNet",
    "https://github.com/inparallel/SaudiNewsNet"
  ]
}