{
  "authors":2,
  "changes":[
    1,
    1,
    0,
    1,
    1,
    0,
    1,
    1,
    0,
    1,
    1,
    0,
    0,
    1,
    1,
    1,
    0,
    0,
    0,
    0,
    0,
    0
  ],
  "era_topic":[
    "Abbasid",
    "Abbasid",
    "Abbasid",
    "Abbasid",
    "Abbasid",
    "Abbasid",
    "Abbasid",
    "Abbasid",
    "Abbasid",
    "Abbasid",
    "Abbasid",
    "Abbasid",
    "Abbasid",
    "Abbasid",
    "Abbasid",
    "Abbasid",
    "Abbasid",
    "Abbasid",
    "Abbasid",
    "Abbasid",
    "Abbasid",
    "Abbasid",
    "Abbasid"
  ],
  "id":[
    "2_479",
    "5_444",
    "2_849",
    "2_257",
    "5_634",
    "2_1309",
    "2_1087",
    "5_238",
    "2_573",
    "2_372",
    "5_236",
    "2_280",
    "2_120",
    "2_1105",
    "5_82",
    "2_111",
    "5_219",
    "5_379",
    "5_267",
    "5_347",
    "5_419",
    "5_529",
    "5_168"
  ],
  "level":"hard",
  "linguistic_resource":[
    "Arabic Poetry Dataset",
    "Arabic Poetry Dataset",
    "Arabic Poetry Dataset",
    "Arabic Poetry Dataset",
    "Arabic Poetry Dataset",
    "Arabic Poetry Dataset",
    "Arabic Poetry Dataset",
    "Arabic Poetry Dataset",
    "Arabic Poetry Dataset",
    "Arabic Poetry Dataset",
    "Arabic Poetry Dataset",
    "Arabic Poetry Dataset",
    "Arabic Poetry Dataset",
    "Arabic Poetry Dataset",
    "Arabic Poetry Dataset",
    "Arabic Poetry Dataset",
    "Arabic Poetry Dataset",
    "Arabic Poetry Dataset",
    "Arabic Poetry Dataset",
    "Arabic Poetry Dataset",
    "Arabic Poetry Dataset",
    "Arabic Poetry Dataset",
    "Arabic Poetry Dataset"
  ],
  "multi-author":1,
  "paragraph-author-names":[
    "أبوالعلاء المعري",
    "الشريف الرضي",
    "أبوالعلاء المعري",
    "أبوالعلاء المعري",
    "الشريف الرضي",
    "أبوالعلاء المعري",
    "أبوالعلاء المعري",
    "الشريف الرضي",
    "أبوالعلاء المعري",
    "أبوالعلاء المعري",
    "الشريف الرضي",
    "أبوالعلاء المعري",
    "أبوالعلاء المعري",
    "أبوالعلاء المعري",
    "الشريف الرضي",
    "أبوالعلاء المعري",
    "الشريف الرضي",
    "الشريف الرضي",
    "الشريف الرضي",
    "الشريف الرضي",
    "الشريف الرضي",
    "الشريف الرضي",
    "الشريف الرضي"
  ],
  "paragraph-author-numbers":[
    2,
    5,
    2,
    2,
    5,
    2,
    2,
    5,
    2,
    2,
    5,
    2,
    2,
    2,
    5,
    2,
    5,
    5,
    5,
    5,
    5,
    5,
    5
  ],
  "paragraph-author-numbers-transliteration":[
    ">bw AlElA’ AlmEry",
    "Al$ryf AlrDy",
    ">bw AlElA’ AlmEry",
    ">bw AlElA’ AlmEry",
    "Al$ryf AlrDy",
    ">bw AlElA’ AlmEry",
    ">bw AlElA’ AlmEry",
    "Al$ryf AlrDy",
    ">bw AlElA’ AlmEry",
    ">bw AlElA’ AlmEry",
    "Al$ryf AlrDy",
    ">bw AlElA’ AlmEry",
    ">bw AlElA’ AlmEry",
    ">bw AlElA’ AlmEry",
    "Al$ryf AlrDy",
    ">bw AlElA’ AlmEry",
    "Al$ryf AlrDy",
    "Al$ryf AlrDy",
    "Al$ryf AlrDy",
    "Al$ryf AlrDy",
    "Al$ryf AlrDy",
    "Al$ryf AlrDy",
    "Al$ryf AlrDy"
  ],
  "url":[
    "https://github.com/inparallel/SaudiNewsNet",
    "https://github.com/inparallel/SaudiNewsNet",
    "https://github.com/inparallel/SaudiNewsNet",
    "https://github.com/inparallel/SaudiNewsNet",
    "https://github.com/inparallel/SaudiNewsNet",
    "https://github.com/inparallel/SaudiNewsNet",
    "https://github.com/inparallel/SaudiNewsNet",
    "https://github.com/inparallel/SaudiNewsNet",
    "https://github.com/inparallel/SaudiNewsNet",
    "https://github.com/inparallel/SaudiNewsNet",
    "https://github.com/inparallel/SaudiNewsNet",
    "https://github.com/inparallel/SaudiNewsNet",
    "https://github.com/inparallel/SaudiNewsNet",
    "https://github.com/inparallel/SaudiNewsNet",
    "https://github.com/inparallel/SaudiNewsNet",
    "https://github.com/inparallel/SaudiNewsNet",
    "https://github.com/inparallel/SaudiNewsNet",
    "https://github.com/inparallel/SaudiNewsNet",
    "https://github.com/inparallel/SaudiNewsNet",
    "https://github.com/inparallel/SaudiNewsNet",
    "https://github.com/inparallel/SaudiNewsNet",
    "https://github.com/inparallel/SaudiNewsNet",
    "https://github.com/inparallel/SaudiNewsNet"
  ]
}