{
  "authors":4,
  "changes":[
    1,
    1,
    1,
    1,
    1,
    0,
    1,
    1,
    1,
    1,
    0,
    1,
    1
  ],
  "era_topic":[
    "Abbasid",
    "Abbasid",
    "Abbasid",
    "Abbasid",
    "Abbasid",
    "Abbasid",
    "Abbasid",
    "Abbasid",
    "Abbasid",
    "Abbasid",
    "Unknown",
    "Unknown",
    "Abbasid",
    "Unknown"
  ],
  "id":[
    "2_550",
    "5_247",
    "3_541",
    "2_1297",
    "3_672",
    "5_49",
    "5_271",
    "2_644",
    "3_497",
    "5_85",
    "4_497",
    "4_798",
    "2_497",
    "4_621"
  ],
  "level":"hard",
  "linguistic_resource":[
    "Arabic Poetry Dataset",
    "Arabic Poetry Dataset",
    "Arabic Poetry Dataset",
    "Arabic Poetry Dataset",
    "Arabic Poetry Dataset",
    "Arabic Poetry Dataset",
    "Arabic Poetry Dataset",
    "Arabic Poetry Dataset",
    "Arabic Poetry Dataset",
    "Arabic Poetry Dataset",
    "Unknown",
    "Unknown",
    "Arabic Poetry Dataset",
    "Unknown"
  ],
  "multi-author":1,
  "paragraph-author-names":[
    "أبوالعلاء المعري",
    "الشريف الرضي",
    "البحتري",
    "أبوالعلاء المعري",
    "البحتري",
    "الشريف الرضي",
    "الشريف الرضي",
    "أبوالعلاء المعري",
    "البحتري",
    "الشريف الرضي",
    "محيي الدين  بن عربي",
    "محيي الدين  بن عربي",
    "أبوالعلاء المعري",
    "محيي الدين  بن عربي"
  ],
  "paragraph-author-numbers":[
    2,
    5,
    3,
    2,
    3,
    5,
    5,
    2,
    3,
    5,
    4,
    4,
    2,
    4
  ],
  "paragraph-author-numbers-transliteration":[
    ">bw AlElA’ AlmEry",
    "Al$ryf AlrDy",
    "AlbHtry",
    ">bw AlElA’ AlmEry",
    "AlbHtry",
    "Al$ryf AlrDy",
    "Al$ryf AlrDy",
    ">bw AlElA’ AlmEry",
    "AlbHtry",
    "Al$ryf AlrDy",
    "mHyy Aldyn bn Erby",
    "mHyy Aldyn bn Erby",
    ">bw AlElA’ AlmEry",
    "mHyy Aldyn bn Erby"
  ],
  "url":[
    "https://github.com/inparallel/SaudiNewsNet",
    "https://github.com/inparallel/SaudiNewsNet",
    "https://github.com/inparallel/SaudiNewsNet",
    "https://github.com/inparallel/SaudiNewsNet",
    "https://github.com/inparallel/SaudiNewsNet",
    "https://github.com/inparallel/SaudiNewsNet",
    "https://github.com/inparallel/SaudiNewsNet",
    "https://github.com/inparallel/SaudiNewsNet",
    "https://github.com/inparallel/SaudiNewsNet",
    "https://github.com/inparallel/SaudiNewsNet",
    "Unknown",
    "Unknown",
    "https://github.com/inparallel/SaudiNewsNet",
    "Unknown"
  ]
}