{
  "authors":3,
  "changes":[
    0,
    1,
    0,
    1,
    1,
    1,
    0
  ],
  "era_topic":[
    "Geography",
    "Geography",
    "Abbasid",
    "Abbasid",
    "Geography",
    "Abbasid",
    "Medicine",
    "Medicine"
  ],
  "id":[
    "4_78",
    "4_202",
    "3_132",
    "3_1783",
    "4_426",
    "3_1394",
    "1_132",
    "1_151"
  ],
  "level":"easy",
  "linguistic_resource":[
    "Classical Arabic Dictionary",
    "Classical Arabic Dictionary",
    "Arabic Poetry Dataset",
    "Arabic Poetry Dataset",
    "Classical Arabic Dictionary",
    "Arabic Poetry Dataset",
    "Classical Arabic Dictionary",
    "Classical Arabic Dictionary"
  ],
  "multi-author":1,
  "paragraph-author-names":[
    "أبو القاسم",
    "أبو القاسم",
    "ابن الرومي",
    "ابن الرومي",
    "أبو القاسم",
    "ابن الرومي",
    "بن سينا",
    "بن سينا"
  ],
  "paragraph-author-numbers":[
    4,
    4,
    3,
    3,
    4,
    3,
    1,
    1
  ],
  "paragraph-author-numbers-transliteration":[
    ">bw AlqAsm",
    ">bw AlqAsm",
    "Abn Alrwmy",
    "Abn Alrwmy",
    ">bw AlqAsm",
    "Abn Alrwmy",
    "Ab nsynA",
    "Ab nsynA"
  ],
  "url":[
    "https://shamela.ws",
    "https://shamela.ws",
    "https://github.com/inparallel/SaudiNewsNet",
    "https://github.com/inparallel/SaudiNewsNet",
    "https://shamela.ws",
    "https://github.com/inparallel/SaudiNewsNet",
    "https://shamela.ws",
    "https://shamela.ws"
  ]
}