{
  "authors":5,
  "changes":[
    0,
    0,
    1,
    1,
    0,
    1,
    1,
    1,
    1,
    0,
    1,
    1,
    1,
    1
  ],
  "era_topic":[
    "Literature",
    "Literature",
    "Literature",
    "Abbasid",
    "Abbasid",
    "Abbasid",
    "Literature",
    "Abbasid",
    "Abbasid",
    "Abbasid",
    "Abbasid",
    "Literature",
    "Abbasid",
    "Abbasid",
    "Literature"
  ],
  "id":[
    "4_244",
    "4_5757",
    "4_2135",
    "2_244",
    "3_261",
    "3_847",
    "1_2477",
    "5_165",
    "2_552",
    "5_279",
    "5_403",
    "1_244",
    "2_1699",
    "3_244",
    "1_639"
  ],
  "level":"medium",
  "linguistic_resource":[
    "Classical Arabic Dictionary",
    "Classical Arabic Dictionary",
    "Classical Arabic Dictionary",
    "Arabic Poetry Dataset",
    "Arabic Poetry Dataset",
    "Arabic Poetry Dataset",
    "Classical Arabic Dictionary",
    "Arabic Poetry Dataset",
    "Arabic Poetry Dataset",
    "Arabic Poetry Dataset",
    "Arabic Poetry Dataset",
    "Classical Arabic Dictionary",
    "Arabic Poetry Dataset",
    "Arabic Poetry Dataset",
    "Classical Arabic Dictionary"
  ],
  "multi-author":1,
  "paragraph-author-names":[
    "أبو عمر",
    "أبو عمر",
    "أبو عمر",
    "ابن الرومي",
    "البحتري",
    "البحتري",
    "يحيى الجريرى",
    "مهيار الديلمي",
    "ابن الرومي",
    "مهيار الديلمي",
    "مهيار الديلمي",
    "يحيى الجريرى",
    "ابن الرومي",
    "البحتري",
    "يحيى الجريرى"
  ],
  "paragraph-author-numbers":[
    4,
    4,
    4,
    2,
    3,
    3,
    1,
    5,
    2,
    5,
    5,
    1,
    2,
    3,
    1
  ],
  "paragraph-author-numbers-transliteration":[
    ">bw Emr",
    ">bw Emr",
    ">bw Emr",
    "Abn Alrwmy",
    "AlbHtry",
    "AlbHtry",
    "yHyY AljryrY",
    "mhyAr Aldylmy",
    "Abn Alrwmy",
    "mhyAr Aldylmy",
    "mhyAr Aldylmy",
    "yHyY AljryrY",
    "Abn Alrwmy",
    "AlbHtry",
    "yHyY AljryrY"
  ],
  "url":[
    "https://shamela.ws",
    "https://shamela.ws",
    "https://shamela.ws",
    "https://github.com/inparallel/SaudiNewsNet",
    "https://github.com/inparallel/SaudiNewsNet",
    "https://github.com/inparallel/SaudiNewsNet",
    "https://shamela.ws",
    "https://github.com/inparallel/SaudiNewsNet",
    "https://github.com/inparallel/SaudiNewsNet",
    "https://github.com/inparallel/SaudiNewsNet",
    "https://github.com/inparallel/SaudiNewsNet",
    "https://shamela.ws",
    "https://github.com/inparallel/SaudiNewsNet",
    "https://github.com/inparallel/SaudiNewsNet",
    "https://shamela.ws"
  ]
}