{
  "authors":1,
  "changes":[
    0,
    0,
    0,
    0,
    0,
    0,
    0,
    0,
    0,
    0,
    0,
    0,
    0,
    0,
    0,
    0,
    0,
    0,
    0,
    0,
    0,
    0,
    0,
    0
  ],
  "era_topic":[
    "Literature",
    "Literature",
    "Literature",
    "Literature",
    "Literature",
    "Literature",
    "Literature",
    "Literature",
    "Literature",
    "Literature",
    "Literature",
    "Literature",
    "Literature",
    "Literature",
    "Literature",
    "Literature",
    "Literature",
    "Literature",
    "Literature",
    "Literature",
    "Literature",
    "Literature",
    "Literature",
    "Literature",
    "Literature"
  ],
  "id":[
    "1_7",
    "1_42",
    "1_373",
    "1_1293",
    "1_481",
    "1_1914",
    "1_765",
    "1_2513",
    "1_725",
    "1_942",
    "1_1602",
    "1_764",
    "1_1626",
    "1_1721",
    "1_1626",
    "1_1460",
    "1_1380",
    "1_1060",
    "1_1899",
    "1_1901",
    "1_1297",
    "1_785",
    "1_1687",
    "1_1336",
    "1_1051"
  ],
  "level":"medium",
  "linguistic_resource":[
    "Classical Arabic Dictionary",
    "Classical Arabic Dictionary",
    "Classical Arabic Dictionary",
    "Classical Arabic Dictionary",
    "Classical Arabic Dictionary",
    "Classical Arabic Dictionary",
    "Classical Arabic Dictionary",
    "Classical Arabic Dictionary",
    "Classical Arabic Dictionary",
    "Classical Arabic Dictionary",
    "Classical Arabic Dictionary",
    "Classical Arabic Dictionary",
    "Classical Arabic Dictionary",
    "Classical Arabic Dictionary",
    "Classical Arabic Dictionary",
    "Classical Arabic Dictionary",
    "Classical Arabic Dictionary",
    "Classical Arabic Dictionary",
    "Classical Arabic Dictionary",
    "Classical Arabic Dictionary",
    "Classical Arabic Dictionary",
    "Classical Arabic Dictionary",
    "Classical Arabic Dictionary",
    "Classical Arabic Dictionary",
    "Classical Arabic Dictionary"
  ],
  "multi-author":0,
  "paragraph-author-names":[
    "يحيى الجريرى",
    "يحيى الجريرى",
    "يحيى الجريرى",
    "يحيى الجريرى",
    "يحيى الجريرى",
    "يحيى الجريرى",
    "يحيى الجريرى",
    "يحيى الجريرى",
    "يحيى الجريرى",
    "يحيى الجريرى",
    "يحيى الجريرى",
    "يحيى الجريرى",
    "يحيى الجريرى",
    "يحيى الجريرى",
    "يحيى الجريرى",
    "يحيى الجريرى",
    "يحيى الجريرى",
    "يحيى الجريرى",
    "يحيى الجريرى",
    "يحيى الجريرى",
    "يحيى الجريرى",
    "يحيى الجريرى",
    "يحيى الجريرى",
    "يحيى الجريرى",
    "يحيى الجريرى"
  ],
  "paragraph-author-numbers":[
    1,
    1,
    1,
    1,
    1,
    1,
    1,
    1,
    1,
    1,
    1,
    1,
    1,
    1,
    1,
    1,
    1,
    1,
    1,
    1,
    1,
    1,
    1,
    1,
    1
  ],
  "paragraph-author-numbers-transliteration":[
    "yHyY AljryrY",
    "yHyY AljryrY",
    "yHyY AljryrY",
    "yHyY AljryrY",
    "yHyY AljryrY",
    "yHyY AljryrY",
    "yHyY AljryrY",
    "yHyY AljryrY",
    "yHyY AljryrY",
    "yHyY AljryrY",
    "yHyY AljryrY",
    "yHyY AljryrY",
    "yHyY AljryrY",
    "yHyY AljryrY",
    "yHyY AljryrY",
    "yHyY AljryrY",
    "yHyY AljryrY",
    "yHyY AljryrY",
    "yHyY AljryrY",
    "yHyY AljryrY",
    "yHyY AljryrY",
    "yHyY AljryrY",
    "yHyY AljryrY",
    "yHyY AljryrY",
    "yHyY AljryrY"
  ],
  "url":[
    "https://shamela.ws",
    "https://shamela.ws",
    "https://shamela.ws",
    "https://shamela.ws",
    "https://shamela.ws",
    "https://shamela.ws",
    "https://shamela.ws",
    "https://shamela.ws",
    "https://shamela.ws",
    "https://shamela.ws",
    "https://shamela.ws",
    "https://shamela.ws",
    "https://shamela.ws",
    "https://shamela.ws",
    "https://shamela.ws",
    "https://shamela.ws",
    "https://shamela.ws",
    "https://shamela.ws",
    "https://shamela.ws",
    "https://shamela.ws",
    "https://shamela.ws",
    "https://shamela.ws",
    "https://shamela.ws",
    "https://shamela.ws",
    "https://shamela.ws"
  ]
}