{
  "authors":2,
  "changes":[
    0,
    0,
    0,
    0,
    0,
    0,
    0,
    0,
    1,
    0,
    0,
    0,
    0,
    0,
    0,
    0,
    0,
    0
  ],
  "era_topic":[
    "Literature",
    "Literature",
    "Literature",
    "Literature",
    "Literature",
    "Literature",
    "Literature",
    "Literature",
    "Literature",
    "Abbasid",
    "Abbasid",
    "Abbasid",
    "Abbasid",
    "Abbasid",
    "Abbasid",
    "Abbasid",
    "Abbasid",
    "Abbasid",
    "Abbasid"
  ],
  "id":[
    "4_74",
    "4_1894",
    "4_3422",
    "4_5870",
    "4_1147",
    "4_5779",
    "4_3523",
    "4_4702",
    "4_1518",
    "3_42",
    "3_701",
    "3_883",
    "3_826",
    "3_142",
    "3_61",
    "3_623",
    "3_560",
    "3_171",
    "3_370"
  ],
  "level":"medium",
  "linguistic_resource":[
    "Classical Arabic Dictionary",
    "Classical Arabic Dictionary",
    "Classical Arabic Dictionary",
    "Classical Arabic Dictionary",
    "Classical Arabic Dictionary",
    "Classical Arabic Dictionary",
    "Classical Arabic Dictionary",
    "Classical Arabic Dictionary",
    "Classical Arabic Dictionary",
    "Arabic Poetry Dataset",
    "Arabic Poetry Dataset",
    "Arabic Poetry Dataset",
    "Arabic Poetry Dataset",
    "Arabic Poetry Dataset",
    "Arabic Poetry Dataset",
    "Arabic Poetry Dataset",
    "Arabic Poetry Dataset",
    "Arabic Poetry Dataset",
    "Arabic Poetry Dataset"
  ],
  "multi-author":1,
  "paragraph-author-names":[
    "أبو عمر",
    "أبو عمر",
    "أبو عمر",
    "أبو عمر",
    "أبو عمر",
    "أبو عمر",
    "أبو عمر",
    "أبو عمر",
    "أبو عمر",
    "البحتري",
    "البحتري",
    "البحتري",
    "البحتري",
    "البحتري",
    "البحتري",
    "البحتري",
    "البحتري",
    "البحتري",
    "البحتري"
  ],
  "paragraph-author-numbers":[
    4,
    4,
    4,
    4,
    4,
    4,
    4,
    4,
    4,
    3,
    3,
    3,
    3,
    3,
    3,
    3,
    3,
    3,
    3
  ],
  "paragraph-author-numbers-transliteration":[
    ">bw Emr",
    ">bw Emr",
    ">bw Emr",
    ">bw Emr",
    ">bw Emr",
    ">bw Emr",
    ">bw Emr",
    ">bw Emr",
    ">bw Emr",
    "AlbHtry",
    "AlbHtry",
    "AlbHtry",
    "AlbHtry",
    "AlbHtry",
    "AlbHtry",
    "AlbHtry",
    "AlbHtry",
    "AlbHtry",
    "AlbHtry"
  ],
  "url":[
    "https://shamela.ws",
    "https://shamela.ws",
    "https://shamela.ws",
    "https://shamela.ws",
    "https://shamela.ws",
    "https://shamela.ws",
    "https://shamela.ws",
    "https://shamela.ws",
    "https://shamela.ws",
    "https://github.com/inparallel/SaudiNewsNet",
    "https://github.com/inparallel/SaudiNewsNet",
    "https://github.com/inparallel/SaudiNewsNet",
    "https://github.com/inparallel/SaudiNewsNet",
    "https://github.com/inparallel/SaudiNewsNet",
    "https://github.com/inparallel/SaudiNewsNet",
    "https://github.com/inparallel/SaudiNewsNet",
    "https://github.com/inparallel/SaudiNewsNet",
    "https://github.com/inparallel/SaudiNewsNet",
    "https://github.com/inparallel/SaudiNewsNet"
  ]
}