{
  "authors":1,
  "changes":[
    0,
    0,
    0,
    0,
    0,
    0,
    0,
    0,
    0,
    0,
    0,
    0,
    0,
    0,
    0,
    0,
    0,
    0,
    0,
    0,
    0,
    0,
    0,
    0,
    0,
    0,
    0,
    0,
    0,
    0,
    0,
    0,
    0,
    0
  ],
  "era_topic":[
    "Literature",
    "Literature",
    "Literature",
    "Literature",
    "Literature",
    "Literature",
    "Literature",
    "Literature",
    "Literature",
    "Literature",
    "Literature",
    "Literature",
    "Literature",
    "Literature",
    "Literature",
    "Literature",
    "Literature",
    "Literature",
    "Literature",
    "Literature",
    "Literature",
    "Literature",
    "Literature",
    "Literature",
    "Literature",
    "Literature",
    "Literature",
    "Literature",
    "Literature",
    "Literature",
    "Literature",
    "Literature",
    "Literature",
    "Literature",
    "Literature"
  ],
  "id":[
    "4_1",
    "4_31",
    "4_1294",
    "4_6095",
    "4_4949",
    "4_4038",
    "4_3933",
    "4_1737",
    "4_2992",
    "4_386",
    "4_362",
    "4_516",
    "4_768",
    "4_509",
    "4_4758",
    "4_5507",
    "4_7409",
    "4_4711",
    "4_1754",
    "4_6904",
    "4_1163",
    "4_3664",
    "4_5695",
    "4_3291",
    "4_1501",
    "4_2575",
    "4_6648",
    "4_4953",
    "4_285",
    "4_3051",
    "4_5261",
    "4_3028",
    "4_6995",
    "4_4904",
    "4_1662"
  ],
  "level":"medium",
  "linguistic_resource":[
    "Classical Arabic Dictionary",
    "Classical Arabic Dictionary",
    "Classical Arabic Dictionary",
    "Classical Arabic Dictionary",
    "Classical Arabic Dictionary",
    "Classical Arabic Dictionary",
    "Classical Arabic Dictionary",
    "Classical Arabic Dictionary",
    "Classical Arabic Dictionary",
    "Classical Arabic Dictionary",
    "Classical Arabic Dictionary",
    "Classical Arabic Dictionary",
    "Classical Arabic Dictionary",
    "Classical Arabic Dictionary",
    "Classical Arabic Dictionary",
    "Classical Arabic Dictionary",
    "Classical Arabic Dictionary",
    "Classical Arabic Dictionary",
    "Classical Arabic Dictionary",
    "Classical Arabic Dictionary",
    "Classical Arabic Dictionary",
    "Classical Arabic Dictionary",
    "Classical Arabic Dictionary",
    "Classical Arabic Dictionary",
    "Classical Arabic Dictionary",
    "Classical Arabic Dictionary",
    "Classical Arabic Dictionary",
    "Classical Arabic Dictionary",
    "Classical Arabic Dictionary",
    "Classical Arabic Dictionary",
    "Classical Arabic Dictionary",
    "Classical Arabic Dictionary",
    "Classical Arabic Dictionary",
    "Classical Arabic Dictionary",
    "Classical Arabic Dictionary"
  ],
  "multi-author":0,
  "paragraph-author-names":[
    "أبو عمر",
    "أبو عمر",
    "أبو عمر",
    "أبو عمر",
    "أبو عمر",
    "أبو عمر",
    "أبو عمر",
    "أبو عمر",
    "أبو عمر",
    "أبو عمر",
    "أبو عمر",
    "أبو عمر",
    "أبو عمر",
    "أبو عمر",
    "أبو عمر",
    "أبو عمر",
    "أبو عمر",
    "أبو عمر",
    "أبو عمر",
    "أبو عمر",
    "أبو عمر",
    "أبو عمر",
    "أبو عمر",
    "أبو عمر",
    "أبو عمر",
    "أبو عمر",
    "أبو عمر",
    "أبو عمر",
    "أبو عمر",
    "أبو عمر",
    "أبو عمر",
    "أبو عمر",
    "أبو عمر",
    "أبو عمر",
    "أبو عمر"
  ],
  "paragraph-author-numbers":[
    4,
    4,
    4,
    4,
    4,
    4,
    4,
    4,
    4,
    4,
    4,
    4,
    4,
    4,
    4,
    4,
    4,
    4,
    4,
    4,
    4,
    4,
    4,
    4,
    4,
    4,
    4,
    4,
    4,
    4,
    4,
    4,
    4,
    4,
    4
  ],
  "paragraph-author-numbers-transliteration":[
    ">bw Emr",
    ">bw Emr",
    ">bw Emr",
    ">bw Emr",
    ">bw Emr",
    ">bw Emr",
    ">bw Emr",
    ">bw Emr",
    ">bw Emr",
    ">bw Emr",
    ">bw Emr",
    ">bw Emr",
    ">bw Emr",
    ">bw Emr",
    ">bw Emr",
    ">bw Emr",
    ">bw Emr",
    ">bw Emr",
    ">bw Emr",
    ">bw Emr",
    ">bw Emr",
    ">bw Emr",
    ">bw Emr",
    ">bw Emr",
    ">bw Emr",
    ">bw Emr",
    ">bw Emr",
    ">bw Emr",
    ">bw Emr",
    ">bw Emr",
    ">bw Emr",
    ">bw Emr",
    ">bw Emr",
    ">bw Emr",
    ">bw Emr"
  ],
  "url":[
    "https://shamela.ws",
    "https://shamela.ws",
    "https://shamela.ws",
    "https://shamela.ws",
    "https://shamela.ws",
    "https://shamela.ws",
    "https://shamela.ws",
    "https://shamela.ws",
    "https://shamela.ws",
    "https://shamela.ws",
    "https://shamela.ws",
    "https://shamela.ws",
    "https://shamela.ws",
    "https://shamela.ws",
    "https://shamela.ws",
    "https://shamela.ws",
    "https://shamela.ws",
    "https://shamela.ws",
    "https://shamela.ws",
    "https://shamela.ws",
    "https://shamela.ws",
    "https://shamela.ws",
    "https://shamela.ws",
    "https://shamela.ws",
    "https://shamela.ws",
    "https://shamela.ws",
    "https://shamela.ws",
    "https://shamela.ws",
    "https://shamela.ws",
    "https://shamela.ws",
    "https://shamela.ws",
    "https://shamela.ws",
    "https://shamela.ws",
    "https://shamela.ws",
    "https://shamela.ws"
  ]
}