{
  "authors":3,
  "changes":[
    1,
    0,
    0,
    1,
    1,
    0,
    1,
    1
  ],
  "era_topic":[
    "Abbasid",
    "Abbasid",
    "Abbasid",
    "Abbasid",
    "Abbasid",
    "Literature",
    "Literature",
    "Abbasid",
    "Literature"
  ],
  "id":[
    "3_224",
    "5_4",
    "5_5",
    "5_306",
    "3_4",
    "1_3",
    "1_1653",
    "3_650",
    "1_336"
  ],
  "level":"medium",
  "linguistic_resource":[
    "Arabic Poetry Dataset",
    "Arabic Poetry Dataset",
    "Arabic Poetry Dataset",
    "Arabic Poetry Dataset",
    "Arabic Poetry Dataset",
    "Classical Arabic Dictionary",
    "Classical Arabic Dictionary",
    "Arabic Poetry Dataset",
    "Classical Arabic Dictionary"
  ],
  "multi-author":1,
  "paragraph-author-names":[
    "البحتري",
    "مهيار الديلمي",
    "مهيار الديلمي",
    "مهيار الديلمي",
    "البحتري",
    "يحيى الجريرى",
    "يحيى الجريرى",
    "البحتري",
    "يحيى الجريرى"
  ],
  "paragraph-author-numbers":[
    3,
    5,
    5,
    5,
    3,
    1,
    1,
    3,
    1
  ],
  "paragraph-author-numbers-transliteration":[
    "AlbHtry",
    "mhyAr Aldylmy",
    "mhyAr Aldylmy",
    "mhyAr Aldylmy",
    "AlbHtry",
    "yHyY AljryrY",
    "yHyY AljryrY",
    "AlbHtry",
    "yHyY AljryrY"
  ],
  "url":[
    "https://github.com/inparallel/SaudiNewsNet",
    "https://github.com/inparallel/SaudiNewsNet",
    "https://github.com/inparallel/SaudiNewsNet",
    "https://github.com/inparallel/SaudiNewsNet",
    "https://github.com/inparallel/SaudiNewsNet",
    "https://shamela.ws",
    "https://shamela.ws",
    "https://github.com/inparallel/SaudiNewsNet",
    "https://shamela.ws"
  ]
}